{
    "keep": {
        "days": true,
        "amount": 14
    },
    "auditLog": "C:\\Users\\leelk\\OneDrive\\바탕 화면\\TypeScript\\ts-democracy\\logs\\%DATE%\\.6e1dff8b1f2c0606787d833f555ebc87b679799e-audit.json",
    "files": [
        {
            "date": 1610522114187,
            "name": "C:\\Users\\leelk\\OneDrive\\바탕 화면\\TypeScript\\ts-democracy\\logs\\2021-01-13\\error.log",
            "hash": "a12fdedb2387e709b92f2832f9afd9fa"
        },
        {
            "date": 1610719322922,
            "name": "C:\\Users\\leelk\\OneDrive\\바탕 화면\\TypeScript\\ts-democracy\\logs\\2021-01-15\\error.log",
            "hash": "ff085dd52e5f5b239254d5988f779353"
        },
        {
            "date": 1610895401286,
            "name": "C:\\Users\\leelk\\OneDrive\\바탕 화면\\TypeScript\\ts-democracy\\logs\\2021-01-17\\error.log",
            "hash": "cc792022fa0c4c1a2fc4a48205b907ab"
        },
        {
            "date": 1610896406081,
            "name": "C:\\Users\\leelk\\OneDrive\\바탕 화면\\TypeScript\\ts-democracy\\logs\\2021-01-18\\error.log",
            "hash": "342e981352a832578969dc692b1e26c9"
        },
        {
            "date": 1611057330532,
            "name": "C:\\Users\\leelk\\OneDrive\\바탕 화면\\TypeScript\\ts-democracy\\logs\\2021-01-19\\error.log",
            "hash": "450beb73b16961b35644410b056f342d"
        },
        {
            "date": 1611122095286,
            "name": "C:\\Users\\leelk\\OneDrive\\바탕 화면\\TypeScript\\ts-democracy\\logs\\2021-01-20\\error.log",
            "hash": "119acc056f593efd94a5e605d100ec8d"
        }
    ]
}